ngs_smap-5.0.6.data/data/bin/bedtools
smap/__init__.py
smap/__main__.py
smap/__version__.py
smap/compare.py
smap/delineate.py
smap/haplotype.py
smap/plotting.py
smap/relatedness.py
smap/design/SMAPdesign.py
smap/design/__main__.py
smap/design/design.py
smap/effect_prediction/__init__.py
smap/effect_prediction/__main__.py
smap/effect_prediction/editor.py
smap/effect_prediction/logging_configuration.py
smap/effect_prediction/models.py
smap/effect_prediction/plotting.py
smap/effect_prediction/utils.py
smap/effect_prediction/modifications/__init__.py
smap/effect_prediction/modifications/aggregate.py
smap/effect_prediction/modifications/annotate.py
smap/effect_prediction/modifications/collapse.py
smap/effect_prediction/modifications/discretize.py
smap/effect_prediction/modifications/modification.py
smap/haplotype_window/__init__.py
smap/haplotype_window/arguments.py
smap/haplotype_window/haplotype_window.py
smap/helper/__init__.py
smap/helper/timer_format.py
ngs_smap-5.0.6.dist-info/LICENSE
ngs_smap-5.0.6.dist-info/METADATA
ngs_smap-5.0.6.dist-info/WHEEL
ngs_smap-5.0.6.dist-info/entry_points.txt
ngs_smap-5.0.6.dist-info/top_level.txt
ngs_smap-5.0.6.dist-info/RECORD
