Metadata-Version: 2.2
Name: ngs-smap
Version: 5.0.6
Summary: SMAP is a software package that analyzes next-generation DNA sequencing read mapping distributions and performs haplotype calling to create multi-allelic molecular markers.
Home-page: https://ngs-smap.readthedocs.io/en/latest/
Author-email: tom.ruttink@ilvo.vlaanderen.be
License: GNU General Public License v3 (GPLv3)
Classifier: Programming Language :: Python :: 3
Classifier: License :: OSI Approved :: GNU General Public License v3 (GPLv3)
Requires-Python: !=3.12,>=3.9
License-File: LICENSE
Requires-Dist: colorlog
Requires-Dist: cutadapt
Requires-Dist: biopython
Requires-Dist: gffpandas
Requires-Dist: matplotlib
Requires-Dist: natsort
Requires-Dist: openpyxl
Requires-Dist: pandas
Requires-Dist: plotly
Requires-Dist: pybedtools
Requires-Dist: pysam
Requires-Dist: seaborn
Requires-Dist: typing-extensions
Requires-Dist: gffutils
Requires-Dist: primer3-py
Requires-Dist: tqdm
Requires-Dist: scipy
Requires-Dist: numexpr
Requires-Dist: numpy
Requires-Dist: scanpy
